modules/sysCall.v
`include "mips.h" 

/*
	Module is designed to handle syscalls. If V0 is one this module displays a0. If V0 is 10 this module exits. If V0 is anything else nothing really happens. syscall_control is what determines if the current instruction is infact a syscall.

output - sideeffect of syscall.
*/
module system_call(input wire clk,input wire syscall_control, input wire [31:0] v0, input wire [31:0] a0, input wire [31:0] inst);
	realtime progTime = 0.0;
	integer cycleCounter=1; //start at one due to set up of clock edges
	integer instCounter=0;

	initial begin
		$timeformat(-3, 4, " ms", 10);
		progTime = $realtime;
		$display("StartTime: %t",progTime);

	end

	always @(inst) begin
		instCounter = instCounter + 1;
end


  always @(posedge clk) begin
	cycleCounter = cycleCounter+1;
end

  always @ ( negedge clk ) begin
    if(syscall_control==1) begin
      case(v0)
        32'd1: $display("\na0 = %d",a0);
        32'd10:begin
				 $display("\nSyscall: Exiting Program!");
				 $display("# Clock Cycles: \t%d",cycleCounter);
				 $display("# Instructions: \t%d",instCounter);
				 $display("#Instruction/#Clocks: \t%d", instCounter/cycleCounter);
				 progTime = $realtime;
				 $display("EndTime: %t",progTime);
				 $finish;
				end
        default: $display("Other Syscall");

      endcase


    end

  end

endmodule

modules/data_memory.v
`include "mips.h" 

/*
Module for data memory

Timing works same as the register memory. Read on negedge and write on posedge. Control bits (mem_read and mem_write) determine where output of this module get written to.
*/
module data_memory(input wire clk, input wire mem_read, input wire mem_write, input wire [31:0] address, input wire [31:0] write_data, output reg [31:0] read_data);
  reg [31:0] memory [255:0];

  always @(negedge clk)
    begin
      if(mem_read == 1)
        read_data = memory[address];		//read from data mem on negegde.
    end
  always @(posedge clk)
    begin
      if(mem_write == 1)
        memory[address] = write_data;		//write to data mem on posedge.
    end

endmodule

modules/basicOps.v
/*
Basic and gate.
*/
module and_mod(input wire inOne, input wire inTwo, output wire out);

  assign out = inOne & inTwo; //out == 1 if inOne and inTwo == 1

endmodule


/*
Extends a 16 bit values. Works for 2s compliment by concatinating 16 of the first bit with the orignal value.
*/
module sign_extend(input wire [15:0] in, output reg [31:0] out);

always @(in)
  begin
    out = {{16{in[15]}}, in[15:0]};
  end

endmodule

modules/alu.v
`include "mips.h" 

/*
Module for an ALU. Takes two intputs and has two outputs. One output is the result of the op. The other output is a 1/0 depending on if the result is zero (used for branching).

Operations:
and
or
plus
minus
less than
*/
module alu(input wire [31:0] in1, input wire [31:0] in2, input wire [2:0] aluop, output reg [31:0] out, output wire zero);

  assign zero = (out == 0);

  always @(*) begin
    case(aluop)
      3'b000: out <= in1 & in2;
      3'b001: out <= in1 | in2;
      3'b010: out <= in1 + in2;
      3'b110: out <= in1 - in2;
      3'b111: out <= in1 < in2 ? 1:0;
      default: out <= 0;
    endcase
  end

endmodule

modules/adders.v
/*
Returns adder_out. Out = in1 plus in2. **Note of in1 OR in2 are 'x' then adder_out WILL be 'x'
*/
module adder(input wire [31:0] in1, input wire [31:0] in2, output reg [31:0] adder_out);
  always @(in1)
    begin
      adder_out = in1 + in2;	//add inputs and send on out wire
    end
endmodule

modules/shifts.v
`include "mips.h"

/*
Module in top left of diagram. This shifts the instruction 26->28 bits and then concats the top 4 bits of the adder+4 module. 
*/
module shift_instruction(input wire [25:0] instruction, input wire [31:28] new_pc, output reg [31:0] out);
  always @(instruction) begin
      out = instruction << 2; 	//shift left 2
      out = {new_pc[31:28], out[27:0]};		//concat
  end
endmodule

/*
Shift left by two. No concat on this module unlike above.
*/
module shift(input wire [31:0] instruction, output reg [31:0] shifted);
  always @(instruction)
    shifted = instruction << 2; //shift left 2
endmodule

modules/global_mux.v
`include "mips.h" 

/*
This is a universal mux (any number of bits). If test is zero Ifzero is returned. If test is one ifOne is returned. Output is out.
*/
module global_mux(input wire test, input wire [BITS:0] ifZero, input wire [BITS:0] ifOne, output reg [BITS:0] out);
parameter BITS = 31;
always @(*)
  begin
    out = (test == 0 ? ifZero : ifOne); //terinary operator to determine output of mux.
  end
endmodule

modules/control.v
`include "mips.h" 


/*
This module is designed to send out control signals to other modules. The control signals are determined with the opcode and the function code. With these two inputs we determine if the values of the 10 control signals.
*/
module control (input wire [31:26] opcode,input wire [5:0] funcCode,output reg regDst,output reg jump,output reg branch,output reg memRead,output reg memToReg,output reg [2:0] aluOp,output reg memWrite,output reg aluSrc,output reg regWrite, output reg syscall
);

  always @ ( * ) begin		//one bit control signals usually controlling mux (see data flow to see what these control bits do)
    regDst = opcode == 0 ? 1 : 0;	
    jump = (opcode == 2 || opcode == 3) ? 1 : 0; 
    branch = (opcode == 4 || opcode == 5) ? 1 : 0;
    memRead = opcode == 6'h23 ? 1 : 0;
    memToReg = opcode == 6'h23 ? 1 : 0;
    memWrite = opcode == 6'h2b ? 1 : 0;
    aluSrc = (opcode == 8 || opcode == 6'hd || opcode == 6'h23 || opcode == 6'h2b || opcode == 9) ? 1 : 0;
    regWrite = (opcode == 0 || opcode == 8 || opcode == 6'hd || opcode == 6'h23 || opcode == 9) ? 1 : 0;
    syscall = ( opcode == 0 && funcCode == 6'h0c ) ? 1 : 0;

    if (opcode != 0)		//determines the ALU op so ALU knows which operation to perform.
      case (opcode)
        6'h09: aluOp = 3'b010;
        6'h0d: aluOp = 3'b001;
        6'h23 || 6'h2b: aluOp = 3'b010;
        6'h04 || 6'h05: aluOp = 3'b110;
        default: aluOp = 3'b000;
      endcase

    else
      case (funcCode)				//determine ALU op for non R-type instructions
        6'h20: aluOp = 3'b010;
        6'h22: aluOp = 3'b110;
        6'h24: aluOp = 3'b000;
        6'h25: aluOp = 3'b001;
        6'h2a: aluOp = 3'b111;
        default: aluOp = 3'b000;
      endcase;

  end

endmodule

modules/registers.v
`include "mips.h" 


/*
This module is for register memory. On The negedge of the clk read from register_memory and on posedge we write to the register_memory. All register memory is defaulted to a zero value so that the first ADDIU instruction is able to execute propery
*/
module registers(input wire clk, input wire reg_write, input wire [25:21] reg1, input wire [20:16] reg2, input wire [4:0] use_reg, input wire [31:0] data_in, output reg [31:0] read1, output reg [31:0] read2, output reg [31:0] v0, output reg [31:0] a0, output reg [31:0] t0, output reg [31:0] t1);
  reg [31:0] register_memory [31:0];

	integer i;
  initial begin
	read1 = 32'b0;
	read2 = 32'b0;
	for (i = 0; i<32; i=i+1) begin
		register_memory[i] = 32'b0;		//default memory to zero.
	end


  end
  always @(*)
    begin
	  if(clk) begin
      if(reg_write == 1) begin
        register_memory[use_reg] = data_in;		//write to reg mem.
		end
    end
	else begin
    read1 <= register_memory[reg1];			//read from reg mem.
    read2 <= register_memory[reg2];
	end
    v0 <= register_memory[`v0];
    a0 <= register_memory[`a0];
	t0 <= register_memory[`t0];
	t1 <= register_memory[`t1];
  end

endmodule

modules/instructionMemory.v
/*
Module is designed to store instructions in memory. Accessed to determine what the next instruction of the program is. All of the instructions come from the machine code file add_test.v.

output - next instruction
*/
module instruction_mem(input wire [31:0] addr, output reg [31:0] out);
  reg [31:0] memory [32'h100000:32'h101000];	//memory array
  reg [31:0] out_addr;							//address of instruction

  initial
    begin
      $readmemh("add_test.v", memory);	//read insturctions
    end

  always @(addr)
    begin
        out_addr = addr >> 2;		//shift addr
        out = memory[out_addr];		//get instruction to go out
    end

endmodule

modules/PC.v
`include "mips.h" 


/*
Module designed to keep track of the current PC. On the posedge of the clock this module updates with the new pc to keep the flow of the program moving forward. The value of the next PC is NOT determined in this module, just set.
*/
module PC(input wire clk, input wire [31:0] new_pc, output reg [31:0] current_pc);

initial
  begin
    current_pc = 32'h00400020;
  end

  always @(posedge clk)
    begin
      current_pc = new_pc;
    end

endmodule

ProcessorTestBench.v
/*
This is the test bench for my processor. This module is where all of the wiring between modules is handeled. I attempted to layout this module so it is readable and can be traced back to the data flow diagram. The inline comments explain what each component in this module does. Use the diagram as a reference when refering to this module.
*/ 
module ProcessorTestBench;


//important
reg clk = 0;
wire [31:0] pc;

//wires for connecting modules. Names explain use of wires.
wire [31:0] adder_pc;
wire [31:0] instruction;
wire [31:0] jump_to;
wire [31:0] sign_extend;
wire [31:0] shift_out;
wire [31:0] adder_out;
wire [31:0] read_data1;
wire [31:0] read_data2;
wire [31:0] alu_out;
wire [31:0] data_mem_out;
wire [31:0] v0; //reg v0
wire [31:0] a0; //reg a0
wire [31:0] t0; //reg t0
wire [31:0] t1; //reg t1
wire alu_zero;
wire and_out;

//wires for mux outputs. Same numbers as appear on my data flow diagram
wire [31:0] mux_five_out;
wire [31:0] mux_four_out;
wire [31:0] mux_three_out;
wire [4:0] mux_two_out;
wire [31:0] new_pc;

//control bits. All one bit besides ALU op because more than two ops
wire reg_dest; 
wire jump;
wire branch;
wire mem_read;
wire mem_to_reg;
wire [2:0] aluop;
wire mem_write;
wire alu_src;
wire reg_write;
wire syscall_control;


PC PC_Hold(clk, new_pc, pc); //tracks currentPC and updates to new PC
adder Add_Four(pc, 32'd4, adder_pc);	//add four to PC
instruction_mem inst_mem(pc, instruction);  //mem for instructin
registers registerModule(clk, reg_write, instruction[25:21], instruction[20:16], mux_two_out, mux_five_out, read_data1, read_data2, v0, a0,t0,t1); //reg mem
control controller(instruction[31:26],instruction[5:0], reg_dest, jump, branch, mem_read, mem_to_reg, aluop, mem_write, alu_src, reg_write, syscall); //controller (determines flow of program based on opcode and funcode)
shift_instruction shift_inst(instruction[25:0], adder_pc[31:28], jump_to); //shift and concats instruction

//muxes (named correspond to data flow sheet) .BITS determines size of inputs and outputs
global_mux #(.BITS(31)) muxOne(jump, mux_four_out, jump_to, new_pc);
global_mux #(.BITS(4)) muxTwo(reg_dest, instruction[20:16], instruction[15:11], mux_two_out);
global_mux #(.BITS(31)) muxThree(alu_src, read_data2, sign_extend, mux_three_out);
global_mux #(.BITS(31)) muxFour(and_out, adder_pc, adder_out, mux_four_out);
global_mux #(.BITS(31)) muxFive(mem_to_reg, alu_out, data_mem_out, mux_five_out);

sign_extend my_sign_extend(instruction[15:0], sign_extend); //sign extender 16bits -> 32 bits
shift shiftTwo(sign_extend, shift_out);						//shift by two without concatinating
adder adderTwo(adder_pc, shift_out, adder_out);				//add two inputs (NOT THE PLUS FOUR ADDER)
alu my_alu(read_data1, mux_three_out, aluop, alu_out, alu_zero);	//alu_zero determines result of branch instructions
and_mod my_and(branch, alu_zero, and_out);					//simple and gate
data_memory data_mem(clk, mem_read, mem_write, alu_out, read_data2, data_mem_out); //data memory
system_call my_sys_call(clk,syscall, v0, a0,instruction);			//module used to handle syscalls.




always begin
	//flip clock
  `TICK; clk = ~clk;
	if (clk == 1)
		//display on posedge
  		//$display("Instruction is %x", instruction);
  if(instruction == 0)
    $finish; //end on instruction == 0
end
initial begin
  $dumpfile("test.vcd"); //used for GTKwave
  $dumpvars(0, ProcessorTestBench);
end



endmodule

test.vcd
$date
	Fri Sep 15 16:21:52 2017
$end
$version
	Icarus Verilog
$end
$timescale
	1s
$end
$scope module ProcessorTestBench $end
$var wire 32 ! v0 [31:0] $end
$var wire 32 " t1 [31:0] $end
$var wire 32 # t0 [31:0] $end
$var wire 1 $ syscall $end
$var wire 32 % sign_extend [31:0] $end
$var wire 32 & shift_out [31:0] $end
$var wire 1 ' reg_write $end
$var wire 1 ( reg_dest $end
$var wire 32 ) read_data2 [31:0] $end
$var wire 32 * read_data1 [31:0] $end
$var wire 32 + pc [31:0] $end
$var wire 32 , new_pc [31:0] $end
$var wire 5 - mux_two_out [4:0] $end
$var wire 32 . mux_three_out [31:0] $end
$var wire 32 / mux_four_out [31:0] $end
$var wire 32 0 mux_five_out [31:0] $end
$var wire 1 1 mem_write $end
$var wire 1 2 mem_to_reg $end
$var wire 1 3 mem_read $end
$var wire 32 4 jump_to [31:0] $end
$var wire 1 5 jump $end
$var wire 32 6 instruction [31:0] $end
$var wire 32 7 data_mem_out [31:0] $end
$var wire 1 8 branch $end
$var wire 1 9 and_out $end
$var wire 3 : aluop [2:0] $end
$var wire 1 ; alu_zero $end
$var wire 1 < alu_src $end
$var wire 32 = alu_out [31:0] $end
$var wire 32 > adder_pc [31:0] $end
$var wire 32 ? adder_out [31:0] $end
$var wire 32 @ a0 [31:0] $end
$var reg 1 A clk $end
$scope module Add_Four $end
$var wire 32 B in2 [31:0] $end
$var wire 32 C in1 [31:0] $end
$var reg 32 D adder_out [31:0] $end
$upscope $end
$scope module PC_Hold $end
$var wire 1 A clk $end
$var wire 32 E new_pc [31:0] $end
$var reg 32 F current_pc [31:0] $end
$upscope $end
$scope module adderTwo $end
$var wire 32 G in1 [31:0] $end
$var wire 32 H in2 [31:0] $end
$var reg 32 I adder_out [31:0] $end
$upscope $end
$scope module controller $end
$var wire 6 J funcCode [5:0] $end
$var wire 6 K opcode [31:26] $end
$var reg 3 L aluOp [2:0] $end
$var reg 1 < aluSrc $end
$var reg 1 8 branch $end
$var reg 1 5 jump $end
$var reg 1 3 memRead $end
$var reg 1 2 memToReg $end
$var reg 1 1 memWrite $end
$var reg 1 ( regDst $end
$var reg 1 ' regWrite $end
$var reg 1 $ syscall $end
$upscope $end
$scope module data_mem $end
$var wire 1 A clk $end
$var wire 1 3 mem_read $end
$var wire 1 1 mem_write $end
$var wire 32 M write_data [31:0] $end
$var wire 32 N address [31:0] $end
$var reg 32 O read_data [31:0] $end
$upscope $end
$scope module inst_mem $end
$var wire 32 P addr [31:0] $end
$var reg 32 Q out [31:0] $end
$var reg 32 R out_addr [31:0] $end
$upscope $end
$scope module muxFive $end
$var wire 32 S ifOne [31:0] $end
$var wire 1 2 test $end
$var wire 32 T ifZero [31:0] $end
$var reg 32 U out [31:0] $end
$upscope $end
$scope module muxFour $end
$var wire 32 V ifOne [31:0] $end
$var wire 32 W ifZero [31:0] $end
$var wire 1 9 test $end
$var reg 32 X out [31:0] $end
$upscope $end
$scope module muxOne $end
$var wire 32 Y ifZero [31:0] $end
$var wire 1 5 test $end
$var wire 32 Z ifOne [31:0] $end
$var reg 32 [ out [31:0] $end
$upscope $end
$scope module muxThree $end
$var wire 1 < test $end
$var wire 32 \ ifZero [31:0] $end
$var wire 32 ] ifOne [31:0] $end
$var reg 32 ^ out [31:0] $end
$upscope $end
$scope module muxTwo $end
$var wire 5 _ ifOne [4:0] $end
$var wire 5 ` ifZero [4:0] $end
$var wire 1 ( test $end
$var reg 5 a out [4:0] $end
$upscope $end
$scope module my_alu $end
$var wire 3 b aluop [2:0] $end
$var wire 32 c in2 [31:0] $end
$var wire 1 ; zero $end
$var wire 32 d in1 [31:0] $end
$var reg 32 e out [31:0] $end
$upscope $end
$scope module my_and $end
$var wire 1 8 inOne $end
$var wire 1 ; inTwo $end
$var wire 1 9 out $end
$upscope $end
$scope module my_sign_extend $end
$var wire 16 f in [15:0] $end
$var reg 32 g out [31:0] $end
$upscope $end
$scope module my_sys_call $end
$var wire 1 A clk $end
$var wire 32 h inst [31:0] $end
$var wire 1 $ syscall_control $end
$var wire 32 i v0 [31:0] $end
$var wire 32 j a0 [31:0] $end
$var integer 32 k cycleCounter [31:0] $end
$var integer 32 l instCounter [31:0] $end
$var real 1 m progTime $end
$upscope $end
$scope module registerModule $end
$var wire 1 A clk $end
$var wire 32 n data_in [31:0] $end
$var wire 5 o reg1 [25:21] $end
$var wire 5 p reg2 [20:16] $end
$var wire 1 ' reg_write $end
$var wire 5 q use_reg [4:0] $end
$var reg 32 r a0 [31:0] $end
$var reg 32 s read1 [31:0] $end
$var reg 32 t read2 [31:0] $end
$var reg 32 u t0 [31:0] $end
$var reg 32 v t1 [31:0] $end
$var reg 32 w v0 [31:0] $end
$var integer 32 x i [31:0] $end
$upscope $end
$scope module shiftTwo $end
$var wire 32 y instruction [31:0] $end
$var reg 32 z shifted [31:0] $end
$upscope $end
$scope module shift_inst $end
$var wire 26 { instruction [25:0] $end
$var wire 4 | new_pc [31:28] $end
$var reg 32 } out [31:0] $end
$upscope $end
$upscope $end
$enddefinitions $end
#0
$dumpvars
b1000000000000000000100 }
b0 |
b10000000000000000001 {
b100 z
b1 y
b100000 x
b0 w
b0 v
b0 u
b0 t
b0 s
b0 r
b1000 q
b1000 p
b0 o
b1 n
r0 m
b1 l
b1 k
b0 j
b0 i
b100100000010000000000000000001 h
b1 g
b1 f
b1 e
b0 d
b1 c
b10 b
b1000 a
b1000 `
b0 _
b1 ^
b1 ]
b0 \
b10000000000000000100100 [
b1000000000000000000100 Z
b10000000000000000100100 Y
b10000000000000000100100 X
b10000000000000000100100 W
bx V
b1 U
b1 T
bx S
b100000000000000001000 R
b100100000010000000000000000001 Q
b10000000000000000100000 P
bx O
b1 N
b0 M
b10 L
b1001 K
b1 J
bx I
b100 H
b10000000000000000100100 G
b10000000000000000100000 F
b10000000000000000100100 E
b10000000000000000100100 D
b10000000000000000100000 C
b100 B
0A
b0 @
bx ?
b10000000000000000100100 >
b1 =
1<
0;
b10 :
09
08
bx 7
b100100000010000000000000000001 6
05
b1000000000000000000100 4
03
02
01
b1 0
b10000000000000000100100 /
b1 .
b1000 -
b10000000000000000100100 ,
b10000000000000000100000 +
b0 *
b0 )
0(
1'
b100 &
b1 %
0$
b0 #
b0 "
b0 !
$end
#2
b10 0
b10 U
b10 n
b10 =
b10 N
b10 T
b10 e
b10 "
b10 v
b1 #
b1 u
b10 .
b10 ^
b10 c
b1000 &
b1000 H
b1000 z
b10000000000000000101000 ,
b10000000000000000101000 E
b10000000000000000101000 [
b10 %
b10 ]
b10 g
b10 y
b1001 -
b1001 a
b1001 q
b1001000000000000001000 4
b1001000000000000001000 Z
b1001000000000000001000 }
b10000000000000000101100 ?
b10000000000000000101100 I
b10000000000000000101100 V
b10000000000000000101000 /
b10000000000000000101000 X
b10000000000000000101000 Y
b10 l
b10 f
b1001 `
b10010000000000000010 {
b10 J
b1001 p
b10000000000000000101000 >
b10000000000000000101000 D
b10000000000000000101000 G
b10000000000000000101000 W
b100100000010010000000000000010 6
b100100000010010000000000000010 Q
b100100000010010000000000000010 h
b100000000000000001001 R
b10000000000000000100100 +
b10000000000000000100100 C
b10000000000000000100100 F
b10000000000000000100100 P
b10 k
1A
#4
b10 )
b10 M
b10 \
b10 t
0A
#6
b1 0
b1 U
b1 n
b1 =
b1 N
b1 T
b1 e
b1 !
b1 i
b1 w
b1 .
b1 ^
b1 c
b100 &
b100 H
b100 z
b1 %
b1 ]
b1 g
b1 y
b10 -
b10 a
b10 q
b10000000000000000100 4
b10000000000000000100 Z
b10000000000000000100 }
b10000000000000000101100 ,
b10000000000000000101100 E
b10000000000000000101100 [
b11 l
b1 f
b10 `
b100000000000000001 {
b1 J
b10 p
b10000000000000000110100 ?
b10000000000000000110100 I
b10000000000000000110100 V
b10000000000000000101100 /
b10000000000000000101100 X
b10000000000000000101100 Y
b100100000000100000000000000001 6
b100100000000100000000000000001 Q
b100100000000100000000000000001 h
b100000000000000001010 R
b10000000000000000101100 >
b10000000000000000101100 D
b10000000000000000101100 G
b10000000000000000101100 W
b11 k
b10000000000000000101000 +
b10000000000000000101000 C
b10000000000000000101000 F
b10000000000000000101000 P
1A
#8
b1 )
b1 M
b1 \
b1 t
0A
#10
b1 @
b1 j
b1 r
b1000000010000000 &
b1000000010000000 H
b1000000010000000 z
b10000000000000000110000 ,
b10000000000000000110000 E
b10000000000000000110000 [
b10000000100000 %
b10000000100000 ]
b10000000100000 g
b10000000100000 y
b100 -
b100 a
b100 q
b100101000001000000010000000 4
b100101000001000000010000000 Z
b100101000001000000010000000 }
0<
1(
b10000000000000000110000 /
b10000000000000000110000 X
b10000000000000000110000 Y
b100 l
b10000000100000 f
b100 _
b1000 `
b1001010000010000000100000 {
b100000 J
b0 K
b1000 p
b1001 o
b10000000000000000110000 >
b10000000000000000110000 D
b10000000000000000110000 G
b10000000000000000110000 W
b1001010000010000000100000 6
b1001010000010000000100000 Q
b1001010000010000000100000 h
b100000000000000001011 R
b10000000000000000101100 +
b10000000000000000101100 C
b10000000000000000101100 F
b10000000000000000101100 P
b100 k
1A
#12
b11 0
b11 U
b11 n
b11 =
b11 N
b11 T
b11 e
b10 *
b10 d
b10 s
0A
#14
b0 0
b0 U
b0 n
1;
b0 =
b0 N
b0 T
b0 e
b11 @
b11 j
b11 r
b110000 &
b110000 H
b110000 z
b1100 %
b1100 ]
b1100 g
b1100 y
b0 -
b0 a
b0 q
b110000 4
b110000 Z
b110000 }
b0 :
b0 L
b0 b
1$
b10000000000000000110100 ,
b10000000000000000110100 E
b10000000000000000110100 [
b101 l
b1100 f
b0 _
b0 `
b1100 {
b1100 J
b0 p
b0 o
b10000001000000010110100 ?
b10000001000000010110100 I
b10000001000000010110100 V
b10000000000000000110100 /
b10000000000000000110100 X
b10000000000000000110100 Y
b1100 6
b1100 Q
b1100 h
b100000000000000001100 R
b10000000000000000110100 >
b10000000000000000110100 D
b10000000000000000110100 G
b10000000000000000110100 W
b101 k
b10000000000000000110000 +
b10000000000000000110000 C
b10000000000000000110000 F
b10000000000000000110000 P
1A
#16
b0 .
b0 ^
b0 c
b0 )
b0 M
b0 \
b0 t
b0 *
b0 d
b0 s
0A
#18
b1010 0
b1010 U
b1010 n
b1010 !
b1010 i
b1010 w
0;
b1010 =
b1010 N
b1010 T
b1010 e
b101000 &
b101000 H
b101000 z
b1010 .
b1010 ^
b1010 c
b10000000000000000111000 ,
b10000000000000000111000 E
b10000000000000000111000 [
b1010 %
b1010 ]
b1010 g
b1010 y
b10 -
b10 a
b10 q
b10000000000000101000 4
b10000000000000101000 Z
b10000000000000101000 }
b10 :
b10 L
b10 b
0$
1<
0(
b10000000000000001101000 ?
b10000000000000001101000 I
b10000000000000001101000 V
b10000000000000000111000 /
b10000000000000000111000 X
b10000000000000000111000 Y
b110 l
b1010 f
b10 `
b100000000000001010 {
b1010 J
b1001 K
b10 p
b10000000000000000111000 >
b10000000000000000111000 D
b10000000000000000111000 G
b10000000000000000111000 W
b100100000000100000000000001010 6
b100100000000100000000000001010 Q
b100100000000100000000000001010 h
b100000000000000001101 R
b10000000000000000110100 +
b10000000000000000110100 C
b10000000000000000110100 F
b10000000000000000110100 P
b110 k
1A
#20
b1010 )
b1010 M
b1010 \
b1010 t
0A
#22
b0 0
b0 U
b0 n
1;
b0 =
b0 N
b0 T
b0 e
b110000 &
b110000 H
b110000 z
b1100 %
b1100 ]
b1100 g
b1100 y
b0 -
b0 a
b0 q
b110000 4
b110000 Z
b110000 }
b0 :
b0 L
b0 b
1$
0<
1(
b10000000000000000111100 ,
b10000000000000000111100 E
b10000000000000000111100 [
b111 l
b1100 f
b0 `
b1100 {
b1100 J
b0 K
b0 p
b10000000000000001100100 ?
b10000000000000001100100 I
b10000000000000001100100 V
b10000000000000000111100 /
b10000000000000000111100 X
b10000000000000000111100 Y
b1100 6
b1100 Q
b1100 h
b100000000000000001110 R
b10000000000000000111100 >
b10000000000000000111100 D
b10000000000000000111100 G
b10000000000000000111100 W
b111 k
b10000000000000000111000 +
b10000000000000000111000 C
b10000000000000000111000 F
b10000000000000000111000 P
1A
#24
b0 .
b0 ^
b0 c
b0 )
b0 M
b0 \
b0 t
r24 m
0A
